aaaaa_alljson.pth
alljson.py
alljson-0.2.dist-info/DESCRIPTION.rst
alljson-0.2.dist-info/METADATA
alljson-0.2.dist-info/RECORD
alljson-0.2.dist-info/WHEEL
alljson-0.2.dist-info/metadata.json
alljson-0.2.dist-info/top_level.txt
alljson-0.2.dist-info/zip-safe
