Metadata-Version: 2.0
Name: alljson
Version: 0.2
Summary: Make any type JSON-serializable
Home-page: https://github.com/mbachry/alljson
Author: Marcin Bachry
Author-email: hegel666@gmail.com
License: MIT
Platform: UNKNOWN
Classifier: Development Status :: 4 - Beta
Classifier: Intended Audience :: Developers
Classifier: License :: OSI Approved :: MIT License
Classifier: Natural Language :: English
Classifier: Programming Language :: Python :: 3
Classifier: Programming Language :: Python :: 2.7
Classifier: Programming Language :: Python :: 3.6
Requires-Dist: six
